{
"103":{"id":103,"levelMin":35,"levelMax":54,"name":"600001","petId":15905,"prob":1,"monsterQuality":2,"fleeTime":5400,"rewardDiamondFinder":15,"rewardDiamondKiller":15,"hpMultiple":[191.82,308.2,0.000000734,0],"monsterStation1":5010311,"monsterStation2":5010312,"monsterStation3":5010313,"monsterStation4":5010314,"monsterStation5":5010315,"monsterStation6":5010316},
"104":{"id":104,"levelMin":35,"levelMax":54,"name":"600002","petId":15903,"prob":2,"monsterQuality":3,"fleeTime":3600,"rewardDiamondFinder":10,"rewardDiamondKiller":10,"hpMultiple":[95.91,154.1,0.000000367,0],"monsterStation1":5010411,"monsterStation2":5010412,"monsterStation3":5010413,"monsterStation4":5010414,"monsterStation5":5010415,"monsterStation6":5010416},
"105":{"id":105,"levelMin":35,"levelMax":54,"name":"600003","petId":15902,"prob":3,"monsterQuality":4,"fleeTime":1800,"rewardDiamondFinder":5,"rewardDiamondKiller":5,"hpMultiple":[38.364,61.64,0.0000001468,0],"monsterStation1":5010511,"monsterStation2":5010512,"monsterStation3":5010513,"monsterStation4":5010514,"monsterStation5":5010515,"monsterStation6":5010516},
"203":{"id":203,"levelMin":55,"levelMax":74,"name":"600001","petId":15905,"prob":1,"monsterQuality":2,"fleeTime":5400,"rewardDiamondFinder":15,"rewardDiamondKiller":15,"hpMultiple":[191.82,308.2,0.000000734,0],"monsterStation1":5020311,"monsterStation2":5020312,"monsterStation3":5020313,"monsterStation4":5020314,"monsterStation5":5020315,"monsterStation6":5020316},
"204":{"id":204,"levelMin":55,"levelMax":74,"name":"600002","petId":15903,"prob":2,"monsterQuality":3,"fleeTime":3600,"rewardDiamondFinder":10,"rewardDiamondKiller":10,"hpMultiple":[95.91,154.1,0.000000367,0],"monsterStation1":5020411,"monsterStation2":5020412,"monsterStation3":5020413,"monsterStation4":5020414,"monsterStation5":5020415,"monsterStation6":5020416},
"205":{"id":205,"levelMin":55,"levelMax":74,"name":"600003","petId":15902,"prob":3,"monsterQuality":4,"fleeTime":1800,"rewardDiamondFinder":5,"rewardDiamondKiller":5,"hpMultiple":[38.364,61.64,0.0000001468,0],"monsterStation1":5020511,"monsterStation2":5020512,"monsterStation3":5020513,"monsterStation4":5020514,"monsterStation5":5020515,"monsterStation6":5020516},
"303":{"id":303,"levelMin":75,"levelMax":89,"name":"600001","petId":15905,"prob":1,"monsterQuality":2,"fleeTime":5400,"rewardDiamondFinder":15,"rewardDiamondKiller":15,"hpMultiple":[192.39546,309.1246,0.000000736202,0],"monsterStation1":5030311,"monsterStation2":5030312,"monsterStation3":5030313,"monsterStation4":5030314,"monsterStation5":5030315,"monsterStation6":5030316},
"304":{"id":304,"levelMin":75,"levelMax":89,"name":"600002","petId":15903,"prob":2,"monsterQuality":3,"fleeTime":3600,"rewardDiamondFinder":10,"rewardDiamondKiller":10,"hpMultiple":[96.19773,154.5623,0.000000368101,0],"monsterStation1":5030411,"monsterStation2":5030412,"monsterStation3":5030413,"monsterStation4":5030414,"monsterStation5":5030415,"monsterStation6":5030416},
"305":{"id":305,"levelMin":75,"levelMax":89,"name":"600003","petId":15902,"prob":3,"monsterQuality":4,"fleeTime":1800,"rewardDiamondFinder":5,"rewardDiamondKiller":5,"hpMultiple":[38.479092,61.82492,0.0000001472404,0],"monsterStation1":5030511,"monsterStation2":5030512,"monsterStation3":5030513,"monsterStation4":5030514,"monsterStation5":5030515,"monsterStation6":5030516},
"403":{"id":403,"levelMin":90,"levelMax":300,"name":"600001","petId":15905,"prob":1,"monsterQuality":2,"fleeTime":5400,"rewardDiamondFinder":15,"rewardDiamondKiller":15,"hpMultiple":[207.1656,332.856,0.00000079272,0],"monsterStation1":5040311,"monsterStation2":5040312,"monsterStation3":5040313,"monsterStation4":5040314,"monsterStation5":5040315,"monsterStation6":5040316},
"404":{"id":404,"levelMin":90,"levelMax":300,"name":"600002","petId":15903,"prob":2,"monsterQuality":3,"fleeTime":3600,"rewardDiamondFinder":10,"rewardDiamondKiller":10,"hpMultiple":[103.5828,166.428,0.00000039636,0],"monsterStation1":5040411,"monsterStation2":5040412,"monsterStation3":5040413,"monsterStation4":5040414,"monsterStation5":5040415,"monsterStation6":5040416},
"405":{"id":405,"levelMin":90,"levelMax":300,"name":"600003","petId":15902,"prob":3,"monsterQuality":4,"fleeTime":1800,"rewardDiamondFinder":5,"rewardDiamondKiller":5,"hpMultiple":[41.43312,66.5712,0.000000158544,0],"monsterStation1":5040511,"monsterStation2":5040512,"monsterStation3":5040513,"monsterStation4":5040514,"monsterStation5":5040515,"monsterStation6":5040516}
}
